seven_cloudapp_ppmt/__init__.py
seven_cloudapp_ppmt/route.py
seven_cloudapp_ppmt/handlers/__init__.py
seven_cloudapp_ppmt/handlers/client/__init__.py
seven_cloudapp_ppmt/handlers/client/act.py
seven_cloudapp_ppmt/handlers/client/lottery.py
seven_cloudapp_ppmt/handlers/client/power.py
seven_cloudapp_ppmt/handlers/client/user.py
seven_cloudapp_ppmt/handlers/server/__init__.py
seven_cloudapp_ppmt/handlers/server/act_s.py
seven_cloudapp_ppmt/handlers/server/app_s.py
seven_cloudapp_ppmt/handlers/server/launch_s.py
seven_cloudapp_ppmt/handlers/server/machine_s.py
seven_cloudapp_ppmt/handlers/server/order_s.py
seven_cloudapp_ppmt/handlers/server/power_s.py
seven_cloudapp_ppmt/handlers/server/prize_s.py
seven_cloudapp_ppmt/handlers/server/report_s.py
seven_cloudapp_ppmt/handlers/server/theme_s.py
seven_cloudapp_ppmt/handlers/server/throw_s.py
seven_cloudapp_ppmt/handlers/server/user_s.py
seven_cloudapp_ppmt/models/__init__.py
seven_cloudapp_ppmt/models/power_base_model.py
seven_cloudapp_ppmt/models/db_models/__init__.py
seven_cloudapp_ppmt/models/db_models/act/__init__.py
seven_cloudapp_ppmt/models/db_models/act/act_info_model.py
seven_cloudapp_ppmt/models/db_models/act/act_prize_model.py
seven_cloudapp_ppmt/models/db_models/cms/__init__.py
seven_cloudapp_ppmt/models/db_models/cms/cms_info_model.py
seven_cloudapp_ppmt/models/db_models/launch/__init__.py
seven_cloudapp_ppmt/models/db_models/launch/launch_goods_model.py
seven_cloudapp_ppmt/models/db_models/launch/launch_plan_model.py
seven_cloudapp_ppmt/models/db_models/machine/__init__.py
seven_cloudapp_ppmt/models/db_models/machine/machine_info_model.py
seven_cloudapp_ppmt/models/db_models/prize/__init__.py
seven_cloudapp_ppmt/models/db_models/prize/prize_roster_model.py
seven_cloudapp_ppmt/models/db_models/prop/__init__.py
seven_cloudapp_ppmt/models/db_models/prop/prop_give_model.py
seven_cloudapp_ppmt-1.0.93.dist-info/licenses/LICENSE
seven_cloudapp_ppmt-1.0.93.dist-info/METADATA
seven_cloudapp_ppmt-1.0.93.dist-info/WHEEL
seven_cloudapp_ppmt-1.0.93.dist-info/top_level.txt
seven_cloudapp_ppmt-1.0.93.dist-info/RECORD
