Metadata-Version: 2.4
Name: seven_cloudapp_ppmt
Version: 1.0.93
Summary: seven cloudapp ppmt
Home-page: http://gitlab.tdtech.gao7.com/TaoBaoCloud/seven_cloudapp_ppmt.git
Author: seven
Author-email: tech@gao7.com
License: MIT
Classifier: Topic :: Software Development :: Libraries :: Python Modules
Classifier: Programming Language :: Python
Classifier: Programming Language :: Python :: 3.4
Classifier: Programming Language :: Python :: 3.5
Classifier: Programming Language :: Python :: 3.5
Classifier: Programming Language :: Python :: 3.6
Classifier: Programming Language :: Python :: 3.7
Classifier: Programming Language :: Python :: 3.8
Classifier: Programming Language :: Python :: 3.9
Requires-Python: ~=3.4
License-File: LICENSE
Requires-Dist: seven-cloudapp>=1.0.210
Requires-Dist: bce-python-sdk==0.8.61
Dynamic: author
Dynamic: author-email
Dynamic: classifier
Dynamic: description
Dynamic: description-content-type
Dynamic: home-page
Dynamic: license
Dynamic: license-file
Dynamic: requires-dist
Dynamic: requires-python
Dynamic: summary
